{
	"pages": [
		{

			"path": "pages/index/LoginView",
			"style": {
				"navigationBarTitleText": "登录"
			}
		},
		{

			"path": "pages/index/CourseListView",
			"style": {
				"navigationBarTitleText": "我的课程"
			}
		},
		{

			"path": "pages/index/CourseHomeView",
			"style": {
				"navigationBarTitleText": "课程总览"
			}
		},
		{

			"path": "pages/index/TaskKanbanView",
			"style": {
				"navigationBarTitleText": "任务看板"
			}
		},
		{

			"path": "pages/index/TaskAnalyticsView",
			"style": {
				"navigationBarTitleText": "任务数据看板"
			}
		},
		{

			"path": "pages/index/TaskDetailView",
			"style": {
				"navigationBarTitleText": "任务详情"
			}
		},
		{

			"path": "pages/index/ExcellentWorksView",
			"style": {
				"navigationBarTitleText": "优秀作业"
			}
		},
		{

			"path": "pages/index/AITutorView",
			"style": {
				"navigationBarTitleText": "AI 互动"
			}
		},
		{

			"path": "pages/index/SubmissionView",
			"style": {
				"navigationBarTitleText": "提交作业"
			}
		},

		{

			"path": "pages/index/ProfileView",
			"style": {
				"navigationBarTitleText": "个人中心"
			}
		},
		{

			"path": "pages/index/DataDashboardView",
			"style": { "navigationBarTitleText": "数据中心" }
		},
		{

			"path": "pages/index/SettingsView",
			"style": {
				"navigationBarTitleText": "设置"
			}
		}
	],
	"globalStyle": {
		"navigationBarTextStyle": "black",
		"navigationBarTitleText": "爱从游",
		"navigationBarBackgroundColor": "#FFFFFF",
		"backgroundColor": "#F4F7FA",
		"navigationStyle": "custom"
	},
	"tabBar": {
		"color": "#888888",
		"selectedColor": "#4C8AF2",
		"backgroundColor": "#FFFFFF",
		"borderStyle": "black",
		"list": [
			{
				"pagePath": "pages/index/CourseListView",
				"text": "课程",
				"iconPath": "static/tabs/courses.png",
				"selectedIconPath": "static/tabs/courses_active.png"
			},

			{
				"pagePath": "pages/index/ProfileView",
				"text": "我的",
				"iconPath": "static/tabs/profile.png",
				"selectedIconPath": "static/tabs/profile_active.png"
			}
		]
	},
	"uniIdRouter": {}
}
